{
  "basics": {
    "name": "Ramiro Nicolas Cosa",
    "label": "HealthTech Web Developer | Implementación y procesos clínicos",
    "image": "/me.webp",
    "email": "ramirocosa@gmail.com",
    "phone": "299 5217189",
    "url": "https://ramirocosa.is-a.dev/",
    "summary": "Kinesiólogo con más de 20 años de experiencia en atención domiciliaria, coordinación de servicios y auditoría clínica. Desde 2020 desarrollo herramientas web para digitalizar procesos clínicos y operativos, combinando conocimiento real del dominio sanitario con Next.js, TypeScript, testing, documentación y FHIR. Busco integrarme a equipos HealthTech donde pueda aportar en implementación, análisis funcional y desarrollo aplicado a flujos reales de atención.",
    "location": {
      "address": "Neuquen, Argentina",
      "postalCode": "8300",
      "city": "Neuquen",
      "countryCode": "AR",
      "region": "Neuquen"
    },
    "profiles": [
      {
        "network": "LinkedIn",
        "username": "Ramiro Cosa",
        "url": "https://www.linkedin.com/in/ramicosa/"
      },
      {
        "network": "GitHub",
        "username": "RadikeCosa",
        "url": "https://github.com/RadikeCosa"
      }
    ]
  },
  "work": [
    {
      "name": "Desarrollo web aplicado a producto y operaciones",
      "position": "HealthTech Web Developer",
      "url": "https://github.com/RadikeCosa",
      "startDate": "2020-01-01",
      "endDate": null,
      "summary": "Diseño y desarrollo productos web orientados a procesos reales, con foco en salud digital, reglas de negocio y UX operativa. Trabajo con Next.js y TypeScript, integrando testing, documentación, analytics, persistencia de datos y estándares FHIR según las necesidades de cada proyecto.",
      "highlights": [
        "Plataforma clínica para kinesiología domiciliaria con flujos FHIR",
        "Aplicaciones con reglas de negocio, persistencia y estados temporales",
        "Testing automatizado, documentación técnica y despliegues en Vercel"
      ]
    },
    {
      "name": "Alegra Salud",
      "position": "Coordinador y Auditor de Servicios de Internación Domiciliaria",
      "url": "",
      "startDate": "2013-01-01",
      "endDate": "2024-12-01",
      "summary": "Coordiné servicios de internación domiciliaria, audité prestaciones clínicas y articulé la comunicación entre pacientes, familias, profesionales y equipos internos. Participé en el diseño de procesos operativos y en la creación de un área de cuidados paliativos, gestionando necesidades asistenciales en contextos complejos.",
      "highlights": [
        "Coordinación de equipos multidisciplinarios y servicios domiciliarios",
        "Auditoría clínica y seguimiento de prestaciones",
        "Diseño de procesos y comunicación con familias y profesionales"
      ]
    },
    {
      "name": "CIKAF y práctica clínica privada",
      "position": "Kinesiólogo",
      "url": "",
      "startDate": "2004-01-01",
      "endDate": "2013-01-01",
      "summary": "Atendí pacientes en rehabilitación clínica y deportiva, incluyendo trabajo con equipos de alto rendimiento. Esta práctica consolidó mi capacidad para evaluar necesidades, documentar evolución y adaptar tratamientos en coordinación con pacientes y otros profesionales.",
      "highlights": [
        "Rehabilitación clínica y deportiva",
        "Seguimiento de tratamientos y evolución de pacientes"
      ]
    }
  ],
  "volunteer": [],
  "education": [
    {
      "institution": "Universidad de Helsinki",
      "url": "https://www.helsinki.fi/en",
      "area": "Full Stack Open: desarrollo web, testing y arquitectura de software",
      "studyType": "Curso online",
      "startDate": "2025-01-01",
      "endDate": null,
      "courses": [
        "React",
        "Node.js",
        "Testing",
        "Usuarios, sesiones y permisos"
      ]
    },
    {
      "institution": "Universidad Tecnológica Nacional",
      "url": "https://sysgestion.frba.utn.edu.ar/alumnos/validar_certificado?codigo=CER-QGZFK5SQ-60023",
      "area": "Desarrollo Web Full Stack",
      "studyType": "Diplomatura online",
      "startDate": "2020-03-01",
      "endDate": "2021-03-01",
      "courses": [
        "JavaScript",
        "Backend",
        "Autenticación",
        "Testing",
        "Arquitectura de software"
      ]
    },
    {
      "institution": "Universidad Nacional de Córdoba",
      "url": "https://www.unc.edu.ar/",
      "area": "Licenciatura en Kinesiología y Fisioterapia",
      "studyType": "Carrera de grado",
      "startDate": "1998-01-01",
      "endDate": "2003-12-01",
      "courses": []
    }
  ],
  "awards": [],
  "certificates": [
    {
      "name": "Testing Manual y Automatizado",
      "date": "2022-01-01",
      "issuer": "Argentina Programa",
      "url": ""
    }
  ],
  "publications": [],
  "skills": [
    {
      "name": "Flujos clínicos",
      "level": "Avanzado",
      "keywords": ["Atención domiciliaria", "Coordinación clínica", "Auditoría"]
    },
    {
      "name": "Análisis funcional",
      "level": "Intermedio",
      "keywords": ["Relevamiento", "Reglas de negocio", "Producto"]
    },
    {
      "name": "Diseño de procesos",
      "level": "Avanzado",
      "keywords": ["Operaciones", "Documentación", "Mejora continua"]
    },
    {
      "name": "UX operativa",
      "level": "Intermedio",
      "keywords": ["Flujos de trabajo", "Usuarios internos", "Accesibilidad"]
    },
    {
      "name": "FHIR",
      "level": "Intermedio",
      "keywords": ["HAPI FHIR", "Interoperabilidad", "HealthTech"]
    },
    {
      "name": "Testing",
      "level": "Intermedio",
      "keywords": ["Vitest", "Testing manual", "Regresión"]
    },
    {
      "name": "Documentación",
      "level": "Avanzado",
      "keywords": ["Decisiones técnicas", "Procesos", "Contratos"]
    },
    {
      "name": "Analytics",
      "level": "Intermedio",
      "keywords": ["GA4", "Eventos", "Conversión"]
    },
    {
      "name": "Next.js",
      "level": "Intermedio",
      "keywords": ["App Router", "Server Components", "Server Actions"]
    },
    {
      "name": "React",
      "level": "Intermedio",
      "keywords": ["UI", "Componentes", "Estado"]
    },
    {
      "name": "TypeScript",
      "level": "Intermedio",
      "keywords": ["Tipado", "Modelado", "Frontend", "Backend"]
    },
    {
      "name": "JavaScript",
      "level": "Intermedio",
      "keywords": ["Frontend", "Backend"]
    },
    {
      "name": "Node.js",
      "level": "Intermedio",
      "keywords": ["Backend", "APIs", "Herramientas"]
    },
    {
      "name": "PostgreSQL",
      "level": "Intermedio",
      "keywords": ["Datos relacionales", "Persistencia"]
    },
    {
      "name": "Prisma",
      "level": "Intermedio",
      "keywords": ["ORM", "Migraciones", "Modelado de datos"]
    },
    {
      "name": "Supabase",
      "level": "Intermedio",
      "keywords": ["PostgreSQL", "Realtime", "RLS"]
    },
    {
      "name": "Git",
      "level": "Intermedio",
      "keywords": ["Control de versiones", "Colaboración"]
    },
    {
      "name": "Vercel",
      "level": "Intermedio",
      "keywords": ["Despliegue", "Observabilidad", "Analytics"]
    }
  ],
  "languages": [
    {
      "language": "Español",
      "fluency": "Nativo"
    },
    {
      "language": "Inglés",
      "fluency": "Avanzado"
    }
  ],
  "interests": [
    {
      "name": "Salud digital",
      "keywords": ["HealthTech", "Interoperabilidad", "Procesos clínicos"]
    }
  ],
  "references": [],
  "projects": [
    {
      "name": "Kinesiología a Domicilio",
      "isActive": true,
      "description": "Plataforma clínica liviana y landing de captación para un servicio de kinesiología domiciliaria. Digitaliza consultas, altas administrativas, ciclos de tratamiento, registro de visitas y comunicación operativa con familias.",
      "highlights": [
        "Next.js",
        "TypeScript",
        "FHIR",
        "HAPI FHIR",
        "Vitest",
        "GA4",
        "UX operativa",
        "HealthTech"
      ],
      "github": "https://github.com/RadikeCosa/kinesiologiaadomicilio",
      "url": "https://kinesiologiaadomicilio.vercel.app/"
    },
    {
      "name": "Pronósticos Mundial 2026",
      "isActive": true,
      "description": "Aplicación familiar de pronósticos que modela scoring, persistencia, autenticación simple y estados temporales. Bloquea y revela predicciones según el inicio de cada partido y recalcula posiciones desde resultados reales.",
      "highlights": [
        "Next.js",
        "TypeScript",
        "Prisma",
        "PostgreSQL",
        "Vitest",
        "Reglas de negocio"
      ],
      "github": "https://github.com/RadikeCosa/pronostico-mundial",
      "url": "https://github.com/RadikeCosa/pronostico-mundial"
    },
    {
      "name": "Tutti Frutti Online",
      "isActive": true,
      "description": "Juego multijugador por rondas con categorías configurables, validación en servidor y estado compartido en tiempo real. Los participantes ingresan por invitación y un organizador coordina letras, respuestas y puntuación.",
      "highlights": [
        "Next.js",
        "TypeScript",
        "Supabase",
        "Realtime",
        "Server Actions",
        "RLS"
      ],
      "github": "https://github.com/RadikeCosa/tutti-frutti",
      "url": "https://github.com/RadikeCosa/tutti-frutti"
    },
    {
      "name": "Fira Estudio E-commerce",
      "isActive": true,
      "description": "E-commerce con catálogo, carrito, control de stock y checkout integrado con Mercado Pago. Incluye persistencia en Supabase, procesamiento de webhooks, emails transaccionales, analytics y estrategia de despliegue por ambientes.",
      "highlights": [
        "Next.js",
        "TypeScript",
        "Supabase",
        "Mercado Pago",
        "Webhooks",
        "GA4",
        "Vitest"
      ],
      "github": "https://github.com/RadikeCosa/fira-estudio",
      "url": "https://fira-estudio.vercel.app/"
    }
  ]
}
